biocommons/example/__init__.py
biocommons/example/__main__.py
biocommons/example/marvin.py
biocommons/example/marvin_adjacent_test.py
biocommons/example/quotes.yaml
biocommons/example/tests/__init__.py
biocommons/example/tests/conftest.py
biocommons/example/tests/marvin_subdir_test.py
biocommons.example-0.0.5.dist-info/LICENSE.txt
biocommons.example-0.0.5.dist-info/METADATA
biocommons.example-0.0.5.dist-info/WHEEL
biocommons.example-0.0.5.dist-info/entry_points.txt
biocommons.example-0.0.5.dist-info/top_level.txt
biocommons.example-0.0.5.dist-info/RECORD
