Metadata-Version: 2.1
Name: biocommons.example
Version: 0.0.5
Summary: Example Package
Author-email: biocommons contributors <biocommons-dev@googlegroups.com>
License: Apache License
Project-URL: Homepage, https://github.com/biocommons/biocommons.example
Project-URL: Bug Tracker, https://github.com/biocommons/biocommons.example/issues
Classifier: Programming Language :: Python :: 3
Classifier: Programming Language :: Python :: 3.10
Classifier: Programming Language :: Python :: 3.11
Classifier: Programming Language :: Python :: 3.12
Classifier: License :: OSI Approved :: MIT License
Classifier: Operating System :: OS Independent
Requires-Python: >=3.10
License-File: LICENSE.txt
Requires-Dist: coloredlogs ~=15.0
Requires-Dist: pyyaml ~=6.0
Provides-Extra: dev
Requires-Dist: build ~=0.8 ; extra == 'dev'
Requires-Dist: ipython ~=8.4 ; extra == 'dev'
Requires-Dist: mypy-extensions ~=1.0 ; extra == 'dev'
Requires-Dist: pre-commit ~=3.4 ; extra == 'dev'
Requires-Dist: pytest-cov ~=4.1 ; extra == 'dev'
Requires-Dist: pytest-optional-tests ; extra == 'dev'
Requires-Dist: pytest ~=7.1 ; extra == 'dev'
Requires-Dist: pyright ~=1.1 ; extra == 'dev'
Requires-Dist: ruff ==0.4.4 ; extra == 'dev'
Requires-Dist: tox ~=4.15 ; extra == 'dev'
Requires-Dist: vcrpy ; extra == 'dev'
Provides-Extra: docs
Requires-Dist: mkdocs ; extra == 'docs'
